permgroups/__init__.py
permgroups/groups.py
permgroups/perms.py
permgroups/setsgroups.py
permgroups/simsgroups.py
permgroups/test_alt.py
permgroups/test_cyclic.py
permgroups/test_dihedral.py
permgroups/test_groups.py
permgroups/test_perms.py
permgroups/test_rubik2.py
permgroups/test_rubik2sims.py
permgroups/test_rubik3.py
permgroups/test_rubik3sims.py
permgroups/test_rubik4.py
permgroups/test_setsgroups.py
permgroups/test_simsgroups.py
permgroups/test_sudoku4.py
permgroups/test_sym.py
permgroups-1.0.2.dist-info/LICENSE
permgroups-1.0.2.dist-info/METADATA
permgroups-1.0.2.dist-info/WHEEL
permgroups-1.0.2.dist-info/top_level.txt
permgroups-1.0.2.dist-info/RECORD
