Metadata-Version: 2.1
Name: permgroups
Version: 1.0.2
Summary: Python implementation of permutation groups
Home-page: https://github.com/ufkapano/permgroups
Author: Andrzej Kapanowski
Author-email: andrzej.kapanowski@uj.edu.pl
License: UNKNOWN
Platform: UNKNOWN
Classifier: Programming Language :: Python :: 3
Classifier: License :: OSI Approved :: BSD License
Classifier: Operating System :: OS Independent
Classifier: Topic :: Education
Classifier: Topic :: Scientific/Engineering
Requires-Python: >=3.7
License-File: LICENSE
